entity_context_crawler/__main__.py
entity_context_crawler/cmd/__init__.py
entity_context_crawler/cmd/build_contexts_db.py
entity_context_crawler/cmd/build_matches_db.py
entity_context_crawler/dao/__init__.py
entity_context_crawler/dao/contexts_db.py
entity_context_crawler/dao/matches_db.py
entity_context_crawler/dao/mid2rid_txt.py
entity_context_crawler/util/__init__.py
entity_context_crawler/util/log.py
entity_context_crawler/util/types.py
entity_context_crawler/util/wikipedia.py
entity_context_crawler-2.0.1.dist-info/LICENSE
entity_context_crawler-2.0.1.dist-info/METADATA
entity_context_crawler-2.0.1.dist-info/WHEEL
entity_context_crawler-2.0.1.dist-info/entry_points.txt
entity_context_crawler-2.0.1.dist-info/top_level.txt
entity_context_crawler-2.0.1.dist-info/RECORD
