Metadata-Version: 2.1
Name: entity-context-crawler
Version: 2.0.1
Summary: UNKNOWN
Home-page: UNKNOWN
License: UNKNOWN
Platform: UNKNOWN
License-File: LICENSE
Requires-Dist: lxml
Requires-Dist: spacy
Requires-Dist: wikitextparser
